docsetmcp/__init__.py
docsetmcp/config_loader.py
docsetmcp/py.typed
docsetmcp/server.py
docsetmcp/types.py
docsetmcp/docsets/actionscript.yaml
docsetmcp/docsets/akka.yaml
docsetmcp/docsets/angular.yaml
docsetmcp/docsets/angularjs.yaml
docsetmcp/docsets/ansible.yaml
docsetmcp/docsets/apache_http_server.yaml
docsetmcp/docsets/apple_api_reference.yaml
docsetmcp/docsets/applescript.yaml
docsetmcp/docsets/arduino.yaml
docsetmcp/docsets/backbonejs.yaml
docsetmcp/docsets/bash.yaml
docsetmcp/docsets/boost.yaml
docsetmcp/docsets/bootstrap2.yaml
docsetmcp/docsets/bootstrap3.yaml
docsetmcp/docsets/bootstrap4.yaml
docsetmcp/docsets/bootstrap5.yaml
docsetmcp/docsets/bourbon.yaml
docsetmcp/docsets/c.yaml
docsetmcp/docsets/cappuccino.yaml
docsetmcp/docsets/chai.yaml
docsetmcp/docsets/clojure.yaml
docsetmcp/docsets/cmake.yaml
docsetmcp/docsets/cocos2d.yaml
docsetmcp/docsets/cocos2d_x.yaml
docsetmcp/docsets/cocos3d.yaml
docsetmcp/docsets/codeigniter.yaml
docsetmcp/docsets/coffeescript.yaml
docsetmcp/docsets/coldfusion.yaml
docsetmcp/docsets/common_lisp.yaml
docsetmcp/docsets/compass.yaml
docsetmcp/docsets/couchdb.yaml
docsetmcp/docsets/cpp.yaml
docsetmcp/docsets/css.yaml
docsetmcp/docsets/d3js.yaml
docsetmcp/docsets/dart.yaml
docsetmcp/docsets/django.yaml
docsetmcp/docsets/docker.yaml
docsetmcp/docsets/doctrine_orm.yaml
docsetmcp/docsets/dojo.yaml
docsetmcp/docsets/drupal.yaml
docsetmcp/docsets/elasticsearch.yaml
docsetmcp/docsets/elixir.yaml
docsetmcp/docsets/emacs_lisp.yaml
docsetmcp/docsets/emberjs.yaml
docsetmcp/docsets/emmet.yaml
docsetmcp/docsets/erlang.yaml
docsetmcp/docsets/express.yaml
docsetmcp/docsets/extjs.yaml
docsetmcp/docsets/flask.yaml
docsetmcp/docsets/font_awesome.yaml
docsetmcp/docsets/foundation.yaml
docsetmcp/docsets/go.yaml
docsetmcp/docsets/groovy.yaml
docsetmcp/docsets/grunt.yaml
docsetmcp/docsets/gulp.yaml
docsetmcp/docsets/haml.yaml
docsetmcp/docsets/haskell.yaml
docsetmcp/docsets/html.yaml
docsetmcp/docsets/http.yaml
docsetmcp/docsets/jasmine.yaml
docsetmcp-0.3.3.dist-info/licenses/LICENSE
docsetmcp-0.3.3.dist-info/METADATA
docsetmcp-0.3.3.dist-info/WHEEL
docsetmcp-0.3.3.dist-info/entry_points.txt
docsetmcp-0.3.3.dist-info/top_level.txt
docsetmcp-0.3.3.dist-info/RECORD
