Metadata-Version: 2.4
Name: docsetmcp
Version: 0.3.3
Summary: Search local documentation from Dash through MCP
Home-page: https://github.com/codybrom/docsetmcp
Author: Cody Bromley
Author-email: dev@codybrom.com
Project-URL: Bug Reports, https://github.com/codybrom/docsetmcp/issues
Project-URL: Source, https://github.com/codybrom/docsetmcp
Keywords: mcp model-context-protocol dash documentation llm docset
Classifier: Development Status :: 4 - Beta
Classifier: Intended Audience :: Developers
Classifier: License :: OSI Approved :: MIT License
Classifier: Natural Language :: English
Classifier: Operating System :: MacOS
Classifier: Programming Language :: Python :: 3
Classifier: Programming Language :: Python :: 3.10
Classifier: Programming Language :: Python :: 3.11
Classifier: Programming Language :: Python :: 3.12
Classifier: Programming Language :: Python :: 3.13
Classifier: Topic :: Software Development :: Libraries :: Python Modules
Classifier: Topic :: Software Development :: Documentation
Classifier: Topic :: Utilities
Classifier: Typing :: Typed
Requires-Python: >=3.10
License-File: LICENSE
Requires-Dist: mcp>=1.9.4
Requires-Dist: Brotli>=1.1.0
Requires-Dist: PyYAML>=6.0
Dynamic: author
Dynamic: author-email
Dynamic: classifier
Dynamic: description
Dynamic: description-content-type
Dynamic: home-page
Dynamic: keywords
Dynamic: license-file
Dynamic: project-url
Dynamic: requires-dist
Dynamic: requires-python
Dynamic: summary
